[
  {
    "id": "1c22a042-d502-428f-847c-d069cc98f8e3",
    "at": "2026-06-11T22:28:11.664Z",
    "type": "status-change",
    "deviceId": "room-207-2",
    "deviceName": "x96 Room 207",
    "message": "x96 Room 207 is offline",
    "severity": "critical"
  },
  {
    "id": "e96ce259-09f2-4729-b791-d983fc5247df",
    "at": "2026-06-11T22:28:11.665Z",
    "type": "status-change",
    "deviceId": "room-30-1",
    "deviceName": "x96 Room 30",
    "message": "x96 Room 30 is offline",
    "severity": "critical"
  },
  {
    "id": "80a41433-771d-47e8-aa91-75285763ebc8",
    "at": "2026-06-11T22:28:11.675Z",
    "type": "status-change",
    "deviceId": "room-101-1",
    "deviceName": "x96 Room 101",
    "message": "x96 Room 101 is offline",
    "severity": "critical"
  },
  {
    "id": "3e596f44-8496-418f-9038-6e1e63a61e88",
    "at": "2026-06-11T22:28:12.124Z",
    "type": "status-change",
    "deviceId": "room-16-1",
    "deviceName": "x96 Room 16",
    "message": "x96 Room 16 is offline",
    "severity": "critical"
  },
  {
    "id": "ef1b177e-8254-486c-840b-0ab53644b47d",
    "at": "2026-06-11T22:28:12.134Z",
    "type": "status-change",
    "deviceId": "room-14-1",
    "deviceName": "x96 Room 14",
    "message": "x96 Room 14 is offline",
    "severity": "critical"
  }
]
